pandashells/__init__.py
pandashells/bin/__init__.py
pandashells/bin/p_cdf.py
pandashells/bin/p_config.py
pandashells/bin/p_crypt.py
pandashells/bin/p_df.py
pandashells/bin/p_example_data.py
pandashells/bin/p_facet_grid.py
pandashells/bin/p_format.py
pandashells/bin/p_gui.py
pandashells/bin/p_hist.py
pandashells/bin/p_linspace.py
pandashells/bin/p_lomb_scargle.py
pandashells/bin/p_merge.py
pandashells/bin/p_parallel.py
pandashells/bin/p_plot.py
pandashells/bin/p_rand.py
pandashells/bin/p_regplot.py
pandashells/bin/p_regress.py
pandashells/bin/p_sig_edit.py
pandashells/bin/p_smooth.py
pandashells/example_data/election.csv
pandashells/example_data/electoral_college.csv
pandashells/example_data/sealevel.csv
pandashells/example_data/tips.csv
pandashells/lib/__init__.py
pandashells/lib/arg_lib.py
pandashells/lib/config_lib.py
pandashells/lib/io_lib.py
pandashells/lib/lomb_scargle_lib.py
pandashells/lib/module_checker_lib.py
pandashells/lib/outlier_lib.py
pandashells/lib/parallel_lib.py
pandashells/lib/plot_lib.py
pandashells/lib/temp.py
pandashells/lib/utils_lib.py
pandashells/test/__init__.py
pandashells/test/arg_lib_tests.py
pandashells/test/config_lib_tests.py
pandashells/test/io_lib_tests.py
pandashells/test/lomb_scargle_lib_tests.py
pandashells/test/module_checker_lib_tests.py
pandashells/test/outlier_lib_tests.py
pandashells/test/p_cdf_tests.py
pandashells/test/p_config_test.py
pandashells/test/p_crypt_test.py
pandashells/test/p_df_test.py
pandashells/test/p_facet_grid_test.py
pandashells/test/p_format_test.py
pandashells/test/p_hist_tests.py
pandashells/test/p_linspace_tests.py
pandashells/test/p_lomb_scargle_tests.py
pandashells/test/p_merge_test.py
pandashells/test/p_parallel_tests.py
pandashells/test/p_plot_test.py
pandashells/test/p_rand_tests.py
pandashells/test/p_regplot_test.py
pandashells/test/p_regress_tests.py
pandashells/test/p_sig_edit_test.py
pandashells/test/p_smooth_tests.py
pandashells/test/parallel_lib_tests.py
pandashells/test/plot_lib_tests.py
pandashells-0.3.0.dist-info/LICENSE
pandashells-0.3.0.dist-info/METADATA
pandashells-0.3.0.dist-info/WHEEL
pandashells-0.3.0.dist-info/entry_points.txt
pandashells-0.3.0.dist-info/top_level.txt
pandashells-0.3.0.dist-info/RECORD
